meshcat/__init__.py
meshcat/animation.py
meshcat/commands.py
meshcat/geometry.py
meshcat/path.py
meshcat/transformations.py
meshcat/visualizer.py
meshcat/servers/__init__.py
meshcat/servers/tree.py
meshcat/servers/zmqserver.py
meshcat/tests/__init__.py
meshcat/tests/dummy_websocket_client.py
meshcat/tests/test_drawing.py
meshcat/tests/test_ports.py
meshcat/tests/test_start_server.py
meshcat/tests/data/mesh_0_convex_piece_0.dae
meshcat/tests/data/mesh_0_convex_piece_0.obj
meshcat/tests/data/mesh_0_convex_piece_0.stl_ascii
meshcat/tests/data/mesh_0_convex_piece_0.stl_binary
meshcat_kozlek-0.3.2.dist-info/LICENSE.txt
meshcat_kozlek-0.3.2.dist-info/METADATA
meshcat_kozlek-0.3.2.dist-info/WHEEL
meshcat_kozlek-0.3.2.dist-info/entry_points.txt
meshcat_kozlek-0.3.2.dist-info/top_level.txt
meshcat_kozlek-0.3.2.dist-info/RECORD
